{
  "project_info": {
    "project_number": "62265186094",
    "project_id": "retrospect-accounts",
    "storage_bucket": "retrospect-accounts.appspot.com"
  },
  "client": [
    {
      "client_info": {
        "mobilesdk_app_id": "1:62265186094:android:9ee7b526454039b4fc8cbf",
        "android_client_info": {
          "package_name": "com.cryptos.crypto_app"
        }
      },
      "oauth_client": [
        {
          "client_id": "62265186094-s9jt8scr044u17b5kgdkivksck3tcr4n.apps.googleusercontent.com",
          "client_type": 3
        }
      ],
      "api_key": [
        {
          "current_key": "AIzaSyCGH6lQEqrdbk_uJ8yZklrIu7EQzCZz1TM"
        }
      ],
      "services": {
        "appinvite_service": {
          "other_platform_oauth_client": [
            {
              "client_id": "62265186094-s9jt8scr044u17b5kgdkivksck3tcr4n.apps.googleusercontent.com",
              "client_type": 3
            }
          ]
        }
      }
    }
  ],
  "configuration_version": "1"
}